{"trial_id": "0087", "hyperparameters": {"space": [{"class_name": "Int", "config": {"name": "units_1", "default": null, "conditions": [], "min_value": 10, "max_value": 100, "step": 10, "sampling": "linear"}}, {"class_name": "Float", "config": {"name": "dropout", "default": 0.0, "conditions": [], "min_value": 0.0, "max_value": 0.5, "step": 0.1, "sampling": "linear"}}, {"class_name": "Boolean", "config": {"name": "add_second_layer", "default": false, "conditions": []}}, {"class_name": "Choice", "config": {"name": "optimizer", "default": "sgd", "conditions": [], "values": ["sgd", "adam", "rmsprop"], "ordered": false}}, {"class_name": "Float", "config": {"name": "learning_rate", "default": 0.0001, "conditions": [], "min_value": 0.0001, "max_value": 0.01, "step": null, "sampling": "log"}}, {"class_name": "Int", "config": {"name": "units_2", "default": null, "conditions": [], "min_value": 10, "max_value": 50, "step": 10, "sampling": "linear"}}], "values": {"units_1": 100, "dropout": 0.30000000000000004, "add_second_layer": true, "optimizer": "sgd", "learning_rate": 0.0003604375517159215, "units_2": 50, "tuner/epochs": 50, "tuner/initial_epoch": 0, "tuner/bracket": 0, "tuner/round": 0}}, "metrics": {"metrics": {"accuracy": {"direction": "max", "observations": [{"value": [0.587522029876709], "step": 49}]}, "loss": {"direction": "min", "observations": [{"value": [0.7873718738555908], "step": 49}]}, "val_accuracy": {"direction": "max", "observations": [{"value": [0.7386831045150757], "step": 49}]}, "val_loss": {"direction": "min", "observations": [{"value": [0.7889662981033325], "step": 49}]}}}, "score": 0.7386831045150757, "best_step": 49, "status": "COMPLETED", "message": null}